seabed/__init__.py
seabed/base.py
seabed/ngdc.py
seabed/utilities.py
seabed-1.0.1.dist-info/LICENSE
seabed-1.0.1.dist-info/METADATA
seabed-1.0.1.dist-info/WHEEL
seabed-1.0.1.dist-info/top_level.txt
seabed-1.0.1.dist-info/RECORD
