Metadata-Version: 2.1
Name: seabed
Version: 1.0.1
Summary: NGDC seabed descriptions
Home-page: https://github.com/noaa-ocs-modeling/seabed.git
Author: zacharyburnettNOAA
Author-email: zachary.burnett@noaa.gov
License: CC0
Platform: UNKNOWN
Requires-Python: >=3.6
Requires-Dist: bs4
Requires-Dist: geopandas
Requires-Dist: numpy
Requires-Dist: pandas
Requires-Dist: pyproj
Requires-Dist: requests
Requires-Dist: requests-futures
Provides-Extra: development
Requires-Dist: oitnb ; extra == 'development'
Provides-Extra: testing
Requires-Dist: flake8 ; extra == 'testing'
Requires-Dist: pytest ; extra == 'testing'
Requires-Dist: pytest-cov ; extra == 'testing'
